CHANGES.txt
CONTRIBUTORS.txt
MANIFEST.in
README.txt
setup.cfg
setup.py
Products/__init__.py
Products.pressKit.egg-info/PKG-INFO
Products.pressKit.egg-info/SOURCES.txt
Products.pressKit.egg-info/dependency_links.txt
Products.pressKit.egg-info/entry_points.txt
Products.pressKit.egg-info/namespace_packages.txt
Products.pressKit.egg-info/not-zip-safe
Products.pressKit.egg-info/paster_plugins.txt
Products.pressKit.egg-info/requires.txt
Products.pressKit.egg-info/top_level.txt
Products/pressKit/README.txt
Products/pressKit/__init__.py
Products/pressKit/config.py
Products/pressKit/configure.zcml
Products/pressKit/browser/__init__.py
Products/pressKit/browser/configure.zcml
Products/pressKit/browser/download.py
Products/pressKit/browser/presskit_view.pt
Products/pressKit/browser/views.py
Products/pressKit/content/__init__.py
Products/pressKit/content/configure.zcml
Products/pressKit/content/presskit.py
Products/pressKit/interfaces/__init__.py
Products/pressKit/interfaces/presskit.py
Products/pressKit/portlets/__init__.py
Products/pressKit/portlets/configure.zcml
Products/pressKit/profiles/default/factorytool.xml
Products/pressKit/profiles/default/metadata.xml
Products/pressKit/profiles/default/portlets.xml
Products/pressKit/profiles/default/rolemap.xml
Products/pressKit/profiles/default/types.xml
Products/pressKit/profiles/default/types/Press_Kit.xml
Products/pressKit/tests/__init__.py
Products/pressKit/tests/base.py
Products/pressKit/tests/test_doctest.py
docs/HISTORY.txt
docs/INSTALL.txt
docs/LICENSE.GPL
docs/LICENSE.txt