Metadata-Version: 1.0
Name: Products.pressKit
Version: 0.1
Summary: Folderish type to hold press release files, downloadable zip bundle functionality
Home-page: http://svn.plone.org/svn/collective/
Author: David Jonas
Author-email: david@intk.com
License: GPL
Keywords: folder press kit zip
Platform: UNKNOWN
Classifier: Framework :: Plone
Classifier: Intended Audience :: Developers
Classifier: License :: OSI Approved :: GNU General Public License (GPL)
